logsy/__init__.py
logsy/formatter.py
logsy-1.0.0.dist-info/licenses/LICENSE
logsy-1.0.0.dist-info/METADATA
logsy-1.0.0.dist-info/WHEEL
logsy-1.0.0.dist-info/top_level.txt
logsy-1.0.0.dist-info/RECORD
